{
    "Municipios": {
        "Aguascalientes": {
            "Localidades": [
                "Aguascalientes",
                "Ampliacion De Calvillito (Colonia La Herrada)",
                "Ardillas De Abajo (Las Ardillas)",
                "Arellano",
                "Bajio Los Vazquez",
                "Buenavista De Peñuelas",
                "Cañada Grande De Cotorina",
                "Cabecita 3 Marias (Rancho Nuevo)",
                "Calvillito (Barrio De La Escuela)",
                "Centro De Arriba (El Taray)",
                "Cieneguilla (La Lumbrera)",
                "Colonia Che Guevara",
                "Comunidad El Rocio",
                "Congregacion San Antonio 1O. De Los Pedroza",
                "Cotorina (Coyotes)",
                "Cuauhtemoc (Las Palomas)",
                "Cumbres Iii",
                "Ejido San Antonio De Los Pedroza",
                "Ejido Venustiano Carranza",
                "El Cardon",
                "El Cariñan",
                "El Cedazo (Cedazo De San Antonio)",
                "El Codo",
                "El Colorado (El Soyatal)",
                "El Conejal",
                "El Crucero",
                "El Crucero De Calvillito",
                "El Duraznillo",
                "El Gigante (Arellano)",
                "El Guarda",
                "El Hotelito",
                "El Jagüey",
                "El Malacate",
                "El Molino",
                "El Niagara (Rancho El Niagara)",
                "El Ocote",
                "El Potrerito",
                "El Refugio De Peñuelas",
                "El Relicario",
                "El Salto De Los Salado",
                "El Tanque De Los Jimenez",
                "El Trigo (Tanque El Trigo)",
                "El Turicate",
                "Estacion Cañada Honda",
                "Fraccionamiento Lomas Del Sur",
                "Gral. Jose Ma. Morelos Y Pavon (Cañada Honda)",
                "Granja Elsa",
                "Granjas Fatima",
                "Hacienda Nueva",
                "Jaltomate",
                "La Esperanza",
                "La Loma De Los Negritos",
                "La Nueva Teresa",
                "La Providencia",
                "Las Animas",
                "Las Palomas",
                "Lomas De Arellano",
                "Lomas De Nueva York",
                "Lomas Del Gachupin",
                "Lomas San Judas Tadeo",
                "Los Amarraderos",
                "Los Caños",
                "Los Cuervos (Los Ojos De Agua)",
                "Los Duron",
                "Los Negritos",
                "Lotes De Arellano",
                "Matamoros",
                "Montoro",
                "Norias De Cedazo (Cedazo Norias De Montoro)",
                "Norias De Ojocaliente",
                "Norias Del Paso Hondo",
                "Norias Del Paso Hondo",
                "Ojo De Agua De Palmitas",
                "Peñuelas (El Cienegal)",
                "Playas De Guadalupe",
                "Pocitos",
                "Puerta De Los Viejitos",
                "Rancho El Refugio No. 2",
                "Rancho Los Pargas",
                "Rancho San Carlos",
                "Rancho San Felipe",
                "San Antonio De Padua",
                "San Antonio De Peñuelas",
                "San Felipe (Viñedos San Felipe)",
                "San Francisco Del Arenal",
                "San Ignacio",
                "San Isidro",
                "San Jose De Buenavista",
                "San Jose De La Ordeña",
                "San Miguel",
                "San Miguelito",
                "San Nicolas De Arriba",
                "San Nicolas De Enmedio",
                "San Pedro Cieneguilla",
                "Santa Cruz De La Presa (La Tlacuacha)",
                "Santa Maria De Gallardo",
                "Soledad De Abajo",
                "Viñedos Cuauhtemoc (Churubusco)",
                "Villa Lic. Jesus Teran (Calvillito)"
            ],
            "Total de Localidades": 99
        },
        "Asientos": {
            "Localidades": [
                "Adolfo Lopez Mateos",
                "Amarillas De Esparza (Amarillas)",
                "Asientos",
                "Bimbaletes Aguascalientes (El Alamo)",
                "Bimbaletes Atlas (Tanque De La Vieja)",
                "Caldera",
                "Charco Azul",
                "Cienega Grande",
                "Clavellinas",
                "Colonia Emancipacion (Borunda)",
                "Colonia Gomez Portugal",
                "Colonia San Pedro",
                "Crisostomos",
                "El Bajio De Los Campos",
                "El Epazote",
                "El Muerto",
                "El Polvo",
                "El Salitre",
                "El Tule",
                "Francisco Villa",
                "Gorriones",
                "Guadalupe De Atlas",
                "Jarillas",
                "Jilotepec",
                "La Dichosa",
                "La Esperanza",
                "La Gloria",
                "La Loma (Tanque De Las Palmitas)",
                "La Tinajuela",
                "Las Adjuntas",
                "Las Fraguas",
                "Las Negritas",
                "Lazaro Cardenas",
                "Los Encinos",
                "Molinos",
                "Noria Del Borrego (Norias)",
                "Ojo De Agua De Los Sauces",
                "Ojo De Agua De Rosales",
                "Pilotos",
                "Pino Suarez (Rancho Viejo)",
                "Plutarco Elias Calles",
                "Rancho El Tepetatillo",
                "San Angel",
                "San Antonio De Los Martinez (San Antonio)",
                "San Gil",
                "San Jose Del Rio",
                "San Rafael De Ocampo",
                "San Vicente",
                "Tanque De Guadalupe",
                "Tanque Viejo",
                "Villa Juarez",
                "Viudas De Poniente"
            ],
            "Total de Localidades": 52
        },
        "Calvillo": {
            "Localidades": [
                "Arroyo Ojocalientillo",
                "Barranca De Portales",
                "Calvillo",
                "Cerro Blanco",
                "Chiquihuitero (San Isidro)",
                "Colomos",
                "Crucero Las Pilas",
                "El Cuervero (Cuerveros)",
                "El Maguey",
                "El Morancillo (Los Arcos)",
                "El Puertecito",
                "El Rodeo",
                "El Salitre",
                "El Sauz",
                "El Sauz De La Labor (El Sauz)",
                "El Tepalcate",
                "El Tepetate De Abajo",
                "El Tepetate De Arriba",
                "El Terrero De La Labor (El Terrero)",
                "El Terrero Del Refugio (El Terrero)",
                "El Zapote De La Labor (El Zapote)",
                "Fracc. Antorchistas",
                "Fracc. Valle Huejucar (Fracc. Popular)",
                "Fraccionamiento Solidaridad",
                "Jaltiche De Abajo",
                "Jaltiche De Arriba",
                "Jardines De San Isidro (Colonia Limon)",
                "La Fortuna",
                "La Fragua",
                "La Hiedra",
                "La Labor",
                "La Media Luna",
                "La Panadera",
                "La Rinconada",
                "La Teresa",
                "Las Animas",
                "Las Duraznillas",
                "Las Tinajas (La Tinaja)",
                "Los Patos",
                "Malpaso",
                "Mesa Del Roble",
                "Mesa Grande",
                "Ojo De Agua",
                "Ojocaliente",
                "Palo Alto",
                "Piedras Chinas",
                "Potrero De Los Lopez",
                "Presa De Los Serna",
                "Puerta De Fragua (Presa La Codorniz)",
                "San Tadeo",
                "Temazcal"
            ],
            "Total de Localidades": 51
        },
        "Cosío": {
            "Localidades": [
                "Cosio",
                "El Durazno",
                "El Refugio De Agua Zarca",
                "El Refugio De Providencia (Providencia)",
                "El Salero",
                "Guadalupito",
                "La Esperanza (El Salerito)",
                "La Punta",
                "Mexiquito",
                "Santa Maria De La Paz",
                "Soledad De Abajo (Estacion De Adames)",
                "Soledad De Arriba",
                "Zacatequillas"
            ],
            "Total de Localidades": 13
        },
        "El Llano": {
            "Localidades": [
                "Centros De Trabajo Por Reubicar",
                "Ejido Montoya",
                "El Centenario",
                "El Consuelo",
                "El Copetillo",
                "El Copetillo (El Moquete)",
                "El Milagro",
                "El Mocho",
                "El Novillo",
                "El Puertecito",
                "El Retoño",
                "El Terremoto",
                "El Tildio",
                "Francisco Sarabia (La Reforma)",
                "La Frontera",
                "La Loma Del Refugio",
                "La Lucita",
                "La Luz",
                "La Tinaja",
                "La Union (La Paz)",
                "Lagunita De Las Flores",
                "Las Flores (El Coton)",
                "Lic. Jesus Teran (El Muerto)",
                "Lomas Del Refugio (La Loma)",
                "Los Conos",
                "Montoya",
                "Ojo De Agua De Crucitas",
                "Palo Alto",
                "Rancho Los Aguilares",
                "San Antonio De La Rosa",
                "San Francisco De Los Viveros",
                "San Geronimo",
                "San Rafael",
                "Sandovales (San Miguel De Los Sandovales)",
                "Santa Clara (Las Mieleras)",
                "Santa Rosa (El Huizache)",
                "Tanque El Coyote (El Coyote)"
            ],
            "Total de Localidades": 37
        },
        "Jesús María": {
            "Localidades": [
                "Arboledas Paso Blanco",
                "Brownsville",
                "Buenavista",
                "Cañada El Rodeo",
                "Corral De Barrancos",
                "Ejido La Guayana (Rancho Seco)",
                "El Aurero",
                "El Cenizo",
                "El Llano",
                "El Maguey",
                "El Refugio",
                "Ex-Hacienda De Milpillas",
                "General Ignacio Zaragoza (Venadero)",
                "Gracias A Dios",
                "Jesus Gomez Portugal (Margaritas)",
                "Jesus Maria",
                "La Florida",
                "La Loma (San Isidro)",
                "La Loma De Valladolid",
                "La Primavera",
                "La Tomatina",
                "Las Jaulas",
                "Los Arquitos",
                "Los Muñoz",
                "Los Ramirez",
                "Los Vazquez",
                "Maravillas",
                "Milpillas De Abajo",
                "Miravalle",
                "Paso Blanco",
                "Pedernal 1O.",
                "Rancho San Miguel Residencial",
                "San Antonio De Los Horcones",
                "San Isidro",
                "Sartenejo",
                "Tapias Viejas",
                "Tepetates",
                "Valladolid",
                "Villas De Guadalupe (La Malobra)"
            ],
            "Total de Localidades": 39
        },
        "Pabellón de Arteaga": {
            "Localidades": [
                "Colonia Gamez Orozco (Puerta De Carboneras)",
                "Colonia Nueva",
                "Colonia Ojo Zarco",
                "Ejido El Mezquite (Ojo De Agua Del Mezquite)",
                "Ejido Ojo Zarco (La Loma)",
                "El Garabato",
                "El Pedregal",
                "Emiliano Zapata",
                "Hacienda El Mezquite",
                "Las Animas",
                "Los Lira",
                "Ojo Zarco",
                "Pabellon De Arteaga",
                "San Agustin De Los Puentes",
                "San Luis De Letras",
                "Santiago",
                "Secadora Miguel Aleman"
            ],
            "Total de Localidades": 17
        },
        "Rincón de Romos": {
            "Localidades": [
                "16 De Septiembre",
                "California",
                "Canal Grande",
                "Ejido Ex-Hacienda De Pabellon De Hidalgo",
                "El Ajiladero",
                "El Bajio",
                "El Milagro",
                "El Salitrillo",
                "El Saucillo",
                "El Valle De Las Delicias",
                "Escaleras",
                "Estacion Rincon De Romos",
                "Estancia De Mosqueira",
                "Fresnillo",
                "La Boquilla",
                "Mar Negro",
                "Morelos",
                "Pabellon De Hidalgo",
                "Puerta Del Muerto (El 15)",
                "Rincon De Romos",
                "San Jacinto",
                "San Juan De La Natura",
                "Tunel De Potrerillo"
            ],
            "Total de Localidades": 23
        },
        "San Francisco de los Romo": {
            "Localidades": [
                "Amapolas Del Rio",
                "Borrotes",
                "Colonia Macario J. Gomez",
                "Ejido Rancho Nuevo",
                "El Chaparral",
                "El Tepetate",
                "Estacion De Chicalote",
                "La Casita",
                "La Concepcion",
                "La Escondida (El Salero)",
                "La Providencia",
                "Loretito (Charco Del Toro)",
                "Medio Kilo",
                "Puertecito De La Virgen",
                "San Francisco De Los Romo",
                "Viñedos Rivier"
            ],
            "Total de Localidades": 16
        },
        "San José de Gracia": {
            "Localidades": [
                "Boca Del Tunel De Potrerillo",
                "El Jocoqui",
                "El Tecongo",
                "La Congoja",
                "Paredes",
                "Potrero De Los Lopez",
                "Rancho Viejo",
                "San Antonio De Los Rios",
                "San Jose De Gracia",
                "Santa Elena De La Cruz (Capadero)",
                "Tunel De Potrerillo"
            ],
            "Total de Localidades": 11
        },
        "Tepezalá": {
            "Localidades": [
                "Arroyo Hondo",
                "Caldera",
                "Carboneras",
                "Colonia Ampliacion Los Hornos (El Lagunazo)",
                "El Aguila",
                "El Barranco",
                "El Carmen",
                "El Chayote",
                "El Gigante",
                "El Porvenir",
                "El Progreso (La Tira)",
                "El Refugio",
                "El Tepozan",
                "La Victoria",
                "Los Alamitos",
                "Mesillas",
                "Ojo De Agua De Los Montes",
                "Puerto De La Concepcion",
                "San Antonio",
                "Tepezala"
            ],
            "Total de Localidades": 20
        }
    },
    "Total de Localidades": 379,
    "Total de Municipios": 11
}